{
  "project_info": {
    "project_number": "196619557717",
    "firebase_url": "https://android-chat-35c33.firebaseio.com",
    "project_id": "android-chat-35c33",
    "storage_bucket": "android-chat-35c33.appspot.com"
  },
  "client": [
    {
      "client_info": {
        "mobilesdk_app_id": "1:196619557717:android:9cc9f83774beb1cd",
        "android_client_info": {
          "package_name": "com.weltek.androidchat"
        }
      },
      "oauth_client": [
        {
          "client_id": "196619557717-pfqtnns4kumckhfg2ajpisofnltimbqe.apps.googleusercontent.com",
          "client_type": 3
        }
      ],
      "api_key": [
        {
          "current_key": "AIzaSyDGxi1NdHgIBZPeqA3MX9uxlWuajxp7sPo"
        }
      ],
      "services": {
        "analytics_service": {
          "status": 1
        },
        "appinvite_service": {
          "status": 1,
          "other_platform_oauth_client": []
        },
        "ads_service": {
          "status": 2
        }
      }
    }
  ],
  "configuration_version": "1"
}